cappa_sqlplag/__init__.py
cappa_sqlplag/sqlplag.py
cappa_sqlplag-1.1.0.dist-info/LICENSE
cappa_sqlplag-1.1.0.dist-info/METADATA
cappa_sqlplag-1.1.0.dist-info/WHEEL
cappa_sqlplag-1.1.0.dist-info/top_level.txt
cappa_sqlplag-1.1.0.dist-info/RECORD
