Metadata-Version: 2.1
Name: cappa-sqlplag
Version: 1.1.0
Summary: SQL-детектор плагиата, предназначенный для использования в комплексе автоматической проверки программ CAPPA
Home-page: https://github.com/vrilad/cappa_sqlplag
Download-URL: https://github.com/vrilad/cappa_sqlplag/releases
Author: vrilad
Keywords: cappa,sql,plagiarism
License-File: LICENSE
